README.md
setup.cfg
setup.py
taiji_utils/BatchCorrect.py
taiji_utils/Clustering.py
taiji_utils/Diff.py
taiji_utils/Doublet.py
taiji_utils/Knee.py
taiji_utils/Normalization.py
taiji_utils/Normalization_New.py
taiji_utils/Spectral.py
taiji_utils/Spectral_v2.py
taiji_utils/Utils.py
taiji_utils/Viz.py
taiji_utils/__init__.py
taiji_utils.egg-info/PKG-INFO
taiji_utils.egg-info/SOURCES.txt
taiji_utils.egg-info/dependency_links.txt
taiji_utils.egg-info/entry_points.txt
taiji_utils.egg-info/not-zip-safe
taiji_utils.egg-info/requires.txt
taiji_utils.egg-info/top_level.txt