Metadata-Version: 1.0
Name: taiji-utils
Version: 0.2.3
Summary: Taiji pipeline
Home-page: https://taiji-pipeline.github.io/
Author: Kai Zhang
Author-email: kai@kzhang.org
License: MIT
Platform: UNKNOWN
